{
    "version": "5.1.0",
    "flags": {},
    "shapes": [
        {
            "label": "box",
            "points": [
                [
                    471,
                    795
                ],
                [
                    1102,
                    1553
                ]
            ],
            "group_id": null,
            "shape_type": "rectangle",
            "flags": {}
        }
    ],
    "imagePath": "04_2_5.jpg",
    "imageData": null,
    "imageHeight": 2016,
    "imageWidth": 1512
}