{
    "version": "5.1.1",
    "flags": {},
    "shapes": [
        {
            "label": "box",
            "points": [
                [
                    480,
                    81
                ],
                [
                    1522,
                    1384
                ]
            ],
            "group_id": null,
            "shape_type": "rectangle",
            "flags": {}
        },
        {
            "label": "damage",
            "points": [
                [
                    1169,
                    1147
                ],
                [
                    1233,
                    1202
                ]
            ],
            "group_id": null,
            "shape_type": "rectangle",
            "flags": {}
        }
    ],
    "imagePath": "07_4_4.jpg",
    "imageData": null,
    "imageHeight": 1512,
    "imageWidth": 2016
}