{
    "version": "5.1.1",
    "flags": {},
    "shapes": [
        {
            "label": "box",
            "points": [
                [
                    377,
                    189
                ],
                [
                    1179,
                    1822
                ]
            ],
            "group_id": null,
            "shape_type": "rectangle",
            "flags": {}
        },
        {
            "label": "damage",
            "points": [
                [
                    888,
                    1306
                ],
                [
                    989,
                    1400
                ]
            ],
            "group_id": null,
            "shape_type": "rectangle",
            "flags": {}
        }
    ],
    "imagePath": "10_4_1.jpg",
    "imageData": null,
    "imageHeight": 2016,
    "imageWidth": 1512
}