{
    "version": "5.1.0",
    "flags": {},
    "shapes": [
        {
            "label": "box",
            "points": [
                [
                    533,
                    338
                ],
                [
                    1868,
                    1188
                ]
            ],
            "group_id": null,
            "shape_type": "rectangle",
            "flags": {}
        }
    ],
    "imagePath": "13_3_1.jpg",
    "imageData": null,
    "imageHeight": 1512,
    "imageWidth": 2016
}