{
    "version": "5.1.1",
    "flags": {},
    "shapes": [
        {
            "label": "box",
            "points": [
                [
                    284,
                    427
                ],
                [
                    1040,
                    1434
                ]
            ],
            "group_id": null,
            "shape_type": "rectangle",
            "flags": {}
        },
        {
            "label": "damage",
            "points": [
                [
                    489,
                    662
                ],
                [
                    575,
                    774
                ]
            ],
            "group_id": null,
            "shape_type": "rectangle",
            "flags": {}
        },
        {
            "label": "damage",
            "points": [
                [
                    672,
                    1247
                ],
                [
                    789,
                    1112
                ]
            ],
            "group_id": null,
            "shape_type": "rectangle",
            "flags": {}
        }
    ],
    "imagePath": "23_2_3.jpg",
    "imageData": null,
    "imageHeight": 2016,
    "imageWidth": 1512
}