{
    "version": "5.1.1",
    "flags": {},
    "shapes": [
        {
            "label": "box",
            "points": [
                [
                    386,
                    399
                ],
                [
                    1273,
                    1662
                ]
            ],
            "group_id": null,
            "shape_type": "rectangle",
            "flags": {}
        },
        {
            "label": "damage",
            "points": [
                [
                    513,
                    1210
                ],
                [
                    594,
                    1282
                ]
            ],
            "group_id": null,
            "shape_type": "rectangle",
            "flags": {}
        }
    ],
    "imagePath": "42_2_4.jpg",
    "imageData": null,
    "imageHeight": 2016,
    "imageWidth": 1512
}